{
	"animations": [
		{
			"offsets": [
				2,
				-209
			],
			"loop": false,
			"fps": 24,
			"anim": "singDOWN",
			"indices": [],
			"name": "Down0"
		},
		{
			"offsets": [
				0,
				-155
			],
			"loop": false,
			"fps": 24,
			"anim": "singUP",
			"indices": [],
			"name": "Up0"
		},
		{
			"offsets": [
				19,
				-193
			],
			"loop": false,
			"fps": 24,
			"anim": "singRIGHT",
			"indices": [],
			"name": "Right0"
		},
		{
			"offsets": [
				0,
				-176
			],
			"loop": false,
			"fps": 24,
			"anim": "idle",
			"indices": [],
			"name": "Idle0"
		},
		{
			"offsets": [
				90,
				-188
			],
			"loop": false,
			"fps": 24,
			"anim": "singLEFT",
			"indices": [],
			"name": "Left0"
		},
		{
			"offsets": [
				0,
				-178
			],
			"loop": true,
			"fps": 24,
			"anim": "hey",
			"indices": [],
			"name": "Scared0"
		}
	],
	"no_antialiasing": false,
	"image": "characters/Dave_insanity_lol",
	"position": [
		150,
		0
	],
	"healthicon": "dave",
	"flip_x": false,
	"healthbar_colors": [
		0,
		102,
		255
	],
	"camera_position": [
		-100,
		230
	],
	"sing_duration": 6.1,
	"scale": 1
}